__init__.py
ignoromenot.py
ignoromenot/__init__.py
ignoromenot/ignoromenot.py
ignoromenot/__pycache__/__init__.cpython-38.pyc
ignoromenot/__pycache__/ignoromenot.cpython-38.pyc
ignoromenot-0.0.9.dist-info/LICENSE
ignoromenot-0.0.9.dist-info/METADATA
ignoromenot-0.0.9.dist-info/WHEEL
ignoromenot-0.0.9.dist-info/entry_points.txt
ignoromenot-0.0.9.dist-info/top_level.txt
ignoromenot-0.0.9.dist-info/RECORD
