Metadata-Version: 2.1
Name: ignoromenot
Version: 0.0.9
Summary: Ignorome finder
Home-page: https://github.com/anphan0828/IgnoroMeNot.git
Author: An Phan
Author-email: <ahphan@iastate.edu>
License: GPLv3
Classifier: Programming Language :: Python :: 3
Classifier: License :: OSI Approved :: GNU General Public License v3 (GPLv3)
Classifier: Operating System :: OS Independent
License-File: LICENSE
Requires-Dist: networkx
Requires-Dist: matplotlib
Requires-Dist: numpy
Requires-Dist: Biopython
Requires-Dist: requests
Requires-Dist: pandas
